jupyterbgnotify/__init__.py
jupyterbgnotify/jupyterbgnotify.py
jupyterbgnotify/js/init.js
jupyterbgnotify/js/notify.js
jupyterbgnotify-0.2.1.dist-info/METADATA
jupyterbgnotify-0.2.1.dist-info/RECORD
jupyterbgnotify-0.2.1.dist-info/WHEEL
jupyterbgnotify-0.2.1.dist-info/top_level.txt
