Metadata-Version: 2.1
Name: jupyterbgnotify
Version: 0.2.1
Summary: A Jupyter Notebook %%magic for Browser Notifications of Cell Completion
Home-page: https://github.com/benmanns/jupyterbgnotify
Author: Benjamin Manns
Author-email: benmanns@gmail.com
License: BSD-3-Clause
Platform: UNKNOWN
Classifier: Programming Language :: Python :: 2.7
Classifier: Programming Language :: Python :: 3.6
Requires-Dist: ipython
Requires-Dist: jupyter
